jimplejson/__init__.py
jimplejson/_speedups.cpython-39-darwin.so
jimplejson/compat.py
jimplejson/decoder.py
jimplejson/encoder.py
jimplejson/errors.py
jimplejson/ordered_dict.py
jimplejson/raw_json.py
jimplejson/scanner.py
jimplejson/tool.py
jimplejson/tests/__init__.py
jimplejson/tests/_cibw_runner.py
jimplejson/tests/test_bigint_as_string.py
jimplejson/tests/test_bitsize_int_as_string.py
jimplejson/tests/test_check_circular.py
jimplejson/tests/test_decimal.py
jimplejson/tests/test_decode.py
jimplejson/tests/test_default.py
jimplejson/tests/test_dump.py
jimplejson/tests/test_encode_basestring_ascii.py
jimplejson/tests/test_encode_for_html.py
jimplejson/tests/test_errors.py
jimplejson/tests/test_fail.py
jimplejson/tests/test_float.py
jimplejson/tests/test_for_json.py
jimplejson/tests/test_indent.py
jimplejson/tests/test_item_sort_key.py
jimplejson/tests/test_iterable.py
jimplejson/tests/test_namedtuple.py
jimplejson/tests/test_pass1.py
jimplejson/tests/test_pass2.py
jimplejson/tests/test_pass3.py
jimplejson/tests/test_raw_json.py
jimplejson/tests/test_recursion.py
jimplejson/tests/test_scanstring.py
jimplejson/tests/test_separators.py
jimplejson/tests/test_speedups.py
jimplejson/tests/test_str_subclass.py
jimplejson/tests/test_subclass.py
jimplejson/tests/test_tool.py
jimplejson/tests/test_tuple.py
jimplejson/tests/test_unicode.py
jimplejson-1.0.0.dist-info/LICENSE.txt
jimplejson-1.0.0.dist-info/METADATA
jimplejson-1.0.0.dist-info/WHEEL
jimplejson-1.0.0.dist-info/top_level.txt
jimplejson-1.0.0.dist-info/RECORD
